spark_gaps_date_rorc_tools/__init__.py
spark_gaps_date_rorc_tools/functions/__init__.py
spark_gaps_date_rorc_tools/functions/gaps_date.py
spark_gaps_date_rorc_tools/utils/__init__.py
spark_gaps_date_rorc_tools/utils/config.py
spark_gaps_date_rorc_tools/utils/dataframe.py
spark_gaps_date_rorc_tools/utils/logger.py
spark_gaps_date_rorc_tools/utils/memory.py
spark_gaps_date_rorc_tools/utils/time_execution.py
spark_gaps_date_rorc_tools/utils/templates/__init__.py
spark_gaps_date_rorc_tools/utils/templates/table.html
spark_gaps_date_rorc_tools-0.2.3.dist-info/LICENSE
spark_gaps_date_rorc_tools-0.2.3.dist-info/METADATA
spark_gaps_date_rorc_tools-0.2.3.dist-info/WHEEL
spark_gaps_date_rorc_tools-0.2.3.dist-info/top_level.txt
spark_gaps_date_rorc_tools-0.2.3.dist-info/RECORD
