Metadata-Version: 2.1
Name: spark-gaps-date-rorc-tools
Version: 0.2.3
Summary: spark_gaps_date_rorc_tools
Home-page: https://github.com/jonaqp/spark_gaps_date_rorc_tools/
Author: Jonathan Quiza
Author-email: jony327@gmail.com
License: UNKNOWN
Download-URL: https://github.com/jonaqp/spark_gaps_date_rorct_tools/archive/main.zip
Keywords: spark,gaps,date
Platform: UNKNOWN
Classifier: Development Status :: 5 - Production/Stable
Classifier: Intended Audience :: Developers
Classifier: Intended Audience :: Science/Research
Classifier: Topic :: Scientific/Engineering :: Artificial Intelligence
Classifier: License :: OSI Approved :: Apache Software License
Classifier: Programming Language :: Python :: 3.9
License-File: LICENSE
Requires-Dist: spark-dataframe-tools
Requires-Dist: fastavro
Requires-Dist: fastparquet
Requires-Dist: pyyaml
